{
  "SigninForm": [
    {
      "id": 1,
      "name": "asdasd",
      "email": "asd@gmail.com"
    },
    {
      "name": "as",
      "email": "asd",
      "id": 2
    },
    {
      "name": "asdasd",
      "email": "12313",
      "id": 3
    },
    {
      "name": "sdfsdf",
      "email": "234",
      "id": 4
    },
    {
      "name": "asd",
      "email": "asd",
      "id": 5
    },
    {
      "name": "asd",
      "email": "asd",
      "id": 6
    },
    {
      "name": "asd",
      "email": "asd",
      "id": 7
    }
  ],
  "comments": [
    {
      "id": 1,
      "body": "some comment",
      "postId": 1
    }
  ],
  "profile": {
    "name": "typicode"
  }
}